ri_sdk/__about__.py
ri_sdk/__init__.py
ri_sdk/exceptions.py
ri_sdk/loggers.py
ri_sdk/py.typed
ri_sdk/utils.py
ri_sdk/contrib/__init__.py
ri_sdk/contrib/lib_finder.py
ri_sdk/sdk_wrapper/__init__.py
ri_sdk/sdk_wrapper/robointellect_base_sdk.py
ri_sdk/sdk_wrapper/robointellect_sdk.py
ri_sdk/types/__init__.py
ri_sdk/types/connector_extend_result.py
ri_sdk/types/connector_i2c_close_all_result.py
ri_sdk/types/connector_i2c_close_result.py
ri_sdk/types/connector_i2c_extend_result.py
ri_sdk/types/connector_i2c_extend_to_model_result.py
ri_sdk/types/connector_i2c_open_result.py
ri_sdk/types/connector_i2c_read_byte_result.py
ri_sdk/types/connector_i2c_read_bytes_result.py
ri_sdk/types/connector_i2c_set_bus_result.py
ri_sdk/types/connector_i2c_state_result.py
ri_sdk/types/connector_i2c_write_byte_result.py
ri_sdk/types/connector_i2c_write_bytes_result.py
ri_sdk/types/create_basic_result.py
ri_sdk/types/create_device_component_result.py
ri_sdk/types/create_group_component_result.py
ri_sdk/types/create_model_component_result.py
ri_sdk/types/destroy_component_result.py
ri_sdk/types/destroy_sdk_result.py
ri_sdk/types/device_model_list_result.py
ri_sdk/types/exec_r_servo_drive_custom_device_init_result.py
ri_sdk/types/exec_r_servo_drive_extend_result.py
ri_sdk/types/exec_r_servo_drive_extend_to_model_result.py
ri_sdk/types/exec_r_servo_drive_get_state_result.py
ri_sdk/types/exec_r_servo_drive_rotate_by_pulse_over_time_result.py
ri_sdk/types/exec_r_servo_drive_rotate_by_pulse_result.py
ri_sdk/types/exec_r_servo_drive_rotate_with_relative_speed_over_time_result.py
ri_sdk/types/exec_r_servo_drive_rotate_with_relative_speed_result.py
ri_sdk/types/exec_r_servo_drive_stop_result.py
ri_sdk/types/exec_rgb_led_extend_result.py
ri_sdk/types/exec_rgb_led_extend_to_model_result.py
ri_sdk/types/exec_rgb_led_flashing_with_frequency_result.py
ri_sdk/types/exec_rgb_led_flashing_with_pause_result.py
ri_sdk/types/exec_rgb_led_flicker_result.py
ri_sdk/types/exec_rgb_led_get_color_result.py
ri_sdk-1.1.1.dist-info/METADATA
ri_sdk-1.1.1.dist-info/WHEEL
ri_sdk-1.1.1.dist-info/RECORD
