Metadata-Version: 2.3
Name: ri-sdk
Version: 1.1.1
Summary: RI SDK Pythonic Wrapper
Project-URL: Homepage, https://github.com/mahenzon/ri-sdk-python-wrapper
Project-URL: Documentation, https://github.com/mahenzon/ri-sdk-python-wrapper
Project-URL: Source code, https://github.com/mahenzon/ri-sdk-python-wrapper
Author-email: Suren Khorenyan <surenkhorenyan@gmail.com>
Maintainer-email: Suren Khorenyan <surenkhorenyan@gmail.com>
License-Expression: MIT
Keywords: RI SDK,RoboHand,RoboIntellect
Classifier: Development Status :: 5 - Production/Stable
Classifier: Environment :: Console
Classifier: Environment :: Other Environment
Classifier: Intended Audience :: Developers
Classifier: Intended Audience :: Education
Classifier: Intended Audience :: Information Technology
Classifier: Intended Audience :: Manufacturing
Classifier: License :: OSI Approved :: MIT License
Classifier: Natural Language :: English
Classifier: Natural Language :: Russian
Classifier: Operating System :: OS Independent
Classifier: Programming Language :: Python
Classifier: Programming Language :: Python :: 3
Classifier: Programming Language :: Python :: 3 :: Only
Classifier: Programming Language :: Python :: 3.7
Classifier: Programming Language :: Python :: 3.8
Classifier: Programming Language :: Python :: 3.9
Classifier: Programming Language :: Python :: 3.10
Classifier: Programming Language :: Python :: 3.11
Classifier: Programming Language :: Python :: 3.12
Classifier: Programming Language :: Python :: 3.13
Classifier: Topic :: Education
Classifier: Topic :: Scientific/Engineering
Classifier: Topic :: Scientific/Engineering :: Human Machine Interfaces
Classifier: Topic :: Software Development
Classifier: Topic :: Software Development :: Code Generators
Classifier: Topic :: Software Development :: Libraries
Classifier: Topic :: System :: Hardware
Classifier: Topic :: Utilities
Classifier: Typing :: Typed
Requires-Python: >=3.7
